video_reader/__init__.py
video_reader/__init__.pyi
video_reader/py.typed
video_reader/video_reader.abi3.so
video_reader.libs/libavcodec-b27b4873.so.62
video_reader.libs/libavdevice-00c0c303.so.62
video_reader.libs/libavfilter-49c48318.so.11
video_reader.libs/libavformat-2f1bf3c7.so.62
video_reader.libs/libavutil-fe198177.so.60
video_reader.libs/libdav1d-1724286f.so.4
video_reader.libs/libfontconfig-b548d5fd.so.1
video_reader.libs/libfreetype-69d47f35.so.6
video_reader.libs/libfribidi-075b4993.so.0
video_reader.libs/libgraphite2-fc53092f.so.3
video_reader.libs/libharfbuzz-75beee09.so.0
video_reader.libs/libnuma-5fa60c80.so.1
video_reader.libs/libpcre-22635e57.so.3
video_reader.libs/libpng16-11497962.so.16
video_reader.libs/libswresample-783b9173.so.6
video_reader.libs/libswscale-8bb4295c.so.9
video_reader.libs/libuuid-950e27f8.so.1
video_reader.libs/libvpx-4f7e1ef6.so.5
video_reader.libs/libx264-7079bcfd.so.155
video_reader.libs/libx265-9ba197f0.so.165
video_reader_rs_next-1.0.0.post3.dist-info/METADATA
video_reader_rs_next-1.0.0.post3.dist-info/WHEEL
video_reader_rs_next-1.0.0.post3.dist-info/licenses/COPYING.GPLv2.FFmpeg
video_reader_rs_next-1.0.0.post3.dist-info/licenses/COPYING.GPLv3.FFmpeg
video_reader_rs_next-1.0.0.post3.dist-info/licenses/LICENSE
video_reader_rs_next-1.0.0.post3.dist-info/licenses/license_notes.md
video_reader_rs_next-1.0.0.post3.dist-info/RECORD
