Metadata-Version: 2.4
Name: video-reader-rs-next
Version: 1.0.0.post3
Classifier: Development Status :: 5 - Production/Stable
Classifier: Intended Audience :: Developers
Classifier: Intended Audience :: Science/Research
Classifier: Topic :: Multimedia :: Video
Classifier: Topic :: Scientific/Engineering :: Artificial Intelligence
Classifier: Programming Language :: Rust
Classifier: Programming Language :: Python :: 3
Classifier: Programming Language :: Python :: 3.9
Classifier: Programming Language :: Python :: 3.10
Classifier: Programming Language :: Python :: 3.11
Classifier: Programming Language :: Python :: 3.12
Classifier: Programming Language :: Python :: 3.13
Classifier: Programming Language :: Python :: 3.14
Classifier: Programming Language :: Python :: Implementation :: CPython
Classifier: License :: OSI Approved :: MIT License
Classifier: Operating System :: MacOS
Classifier: Operating System :: POSIX :: Linux
License-File: LICENSE
License-File: COPYING.GPLv2.FFmpeg
License-File: COPYING.GPLv3.FFmpeg
License-File: license_notes.md
Summary: A Python module for video decoding based on Rust's ffmpeg-next, optimized for ML use cases.
Keywords: video,decoding,ffmpeg,machine-learning,rust,pyo3
Author-email: wizyoung <happyyanghehe@gmail.com>
License-Expression: MIT OR GPL-2.0 OR GPL-3.0
Requires-Python: >=3.9
Project-URL: Homepage, https://github.com/wizyoung/video-reader-rs-next
Project-URL: Issues, https://github.com/wizyoung/video-reader-rs-next/issues
Project-URL: Repository, https://github.com/wizyoung/video-reader-rs-next.git
